cleanup/__init__.py
cleanup/cleanup.py
cleanup/file_types.py
cleanup-1.0.4.dist-info/LICENSE
cleanup-1.0.4.dist-info/METADATA
cleanup-1.0.4.dist-info/WHEEL
cleanup-1.0.4.dist-info/entry_points.txt
cleanup-1.0.4.dist-info/top_level.txt
cleanup-1.0.4.dist-info/RECORD
