Metadata-Version: 2.1
Name: cleanup
Version: 1.0.4
Summary: A simple command line utility that organises files in a directory into subdirectories.
Home-page: https://github.com/faheel/cleanup
Author: Syed Faheel Ahmad
Author-email: faheel@live.in
License: MIT
Project-URL: Bug Reports, https://github.com/faheel/cleanup/issues
Project-URL: Source, https://github.com/faheel/cleanup
Keywords: cleanup file-organiser file-organisation file-management hue docopt
Classifier: Development Status :: 5 - Production/Stable
Classifier: Intended Audience :: End Users/Desktop
Classifier: License :: OSI Approved :: MIT License
Classifier: Programming Language :: Python :: 3
Classifier: Topic :: Utilities
License-File: LICENSE
Requires-Dist: docopt
Requires-Dist: huepy
Provides-Extra: dev
Requires-Dist: pylint; extra == "dev"
